{
  "generated_at": "2026-04-11T15:59:17.203473+02:00",
  "total_sources": 6,
  "results": [
    {
      "source_url": "https://dlstreams.top/player/stream-877.php",
      "source_referer": "https://dlstreams.top/",
      "status": "ok",
      "duration_seconds": 5.27,
      "streams_count": 1,
      "streams": [
        {
          "url": "https://planetary.lovetier.bz/ZonaDAZN/index.m3u8?token=Wm9uYURBWk58bm9fY2hlY2tfaXB8MTc3NTkxNjIzMA==.cb2d48a31935e35dd05e138f1cc4837b99c78ce092ce4b237a34088779a456b2",
          "referer": "https://lovetier.bz/",
          "origin": "https://lovetier.bz",
          "user_agent": "Mozilla/5.0 (Windows NT 10.0; Win64; x64) AppleWebKit/537.36 (KHTML, like Gecko) Chrome/122.0.0.0 Safari/537.36"
        }
      ]
    },
    {
      "source_url": "https://dlstreams.top/player/stream-870.php",
      "source_referer": "https://dlstreams.top/",
      "status": "ok",
      "duration_seconds": 4.94,
      "streams_count": 1,
      "streams": [
        {
          "url": "https://planetary.lovetier.bz/SkySportCalcioIT/index.m3u8?token=U2t5U3BvcnRDYWxjaW9JVHxub19jaGVja19pcHwxNzc1OTE2MjM1.46d8b319ea99b0c4e5d0d7613e7f73692b8ae55656819f615a9ae2db901aba05",
          "referer": "https://lovetier.bz/",
          "origin": "https://lovetier.bz",
          "user_agent": "Mozilla/5.0 (Windows NT 10.0; Win64; x64) AppleWebKit/537.36 (KHTML, like Gecko) Chrome/122.0.0.0 Safari/537.36"
        }
      ]
    },
    {
      "source_url": "https://dlstreams.top/player/stream-461.php",
      "source_referer": "https://dlstreams.top/",
      "status": "ok",
      "duration_seconds": 4.96,
      "streams_count": 1,
      "streams": [
        {
          "url": "https://planetary.lovetier.bz/SkySportUnoIT/index.m3u8?token=U2t5U3BvcnRVbm9JVHxub19jaGVja19pcHwxNzc1OTE2MjQw.9c72cbca88f7cc5ed079d386da438a9082a3edf8c4a84c13574e8a5f325aa7b2",
          "referer": "https://lovetier.bz/",
          "origin": "https://lovetier.bz",
          "user_agent": "Mozilla/5.0 (Windows NT 10.0; Win64; x64) AppleWebKit/537.36 (KHTML, like Gecko) Chrome/122.0.0.0 Safari/537.36"
        }
      ]
    },
    {
      "source_url": "https://dlstreams.top/player/stream-576.php",
      "source_referer": "https://dlstreams.top/",
      "status": "ok",
      "duration_seconds": 4.91,
      "streams_count": 1,
      "streams": [
        {
          "url": "https://planetary.lovetier.bz/SkySportTennisIT/index.m3u8?token=U2t5U3BvcnRUZW5uaXNJVHxub19jaGVja19pcHwxNzc1OTE2MjQ0.9d0a069a693d079f9a8369590f3617a5a7fd0bcdd59669c74020dd875b5e62de",
          "referer": "https://lovetier.bz/",
          "origin": "https://lovetier.bz",
          "user_agent": "Mozilla/5.0 (Windows NT 10.0; Win64; x64) AppleWebKit/537.36 (KHTML, like Gecko) Chrome/122.0.0.0 Safari/537.36"
        }
      ]
    },
    {
      "source_url": "https://dlstreams.top/player/stream-575.php",
      "source_referer": "https://dlstreams.top/",
      "status": "ok",
      "duration_seconds": 5.07,
      "streams_count": 1,
      "streams": [
        {
          "url": "https://planetary.lovetier.bz/SkySportMotoGPIT/index.m3u8?token=U2t5U3BvcnRNb3RvR1BJVHxub19jaGVja19pcHwxNzc1OTE2MjUw.636095f67b56009abb4bbe2e5d63b5d9922310353ea9b144b3b778cf19724868",
          "referer": "https://lovetier.bz/",
          "origin": "https://lovetier.bz",
          "user_agent": "Mozilla/5.0 (Windows NT 10.0; Win64; x64) AppleWebKit/537.36 (KHTML, like Gecko) Chrome/122.0.0.0 Safari/537.36"
        }
      ]
    },
    {
      "source_url": "https://dlstreams.top/player/stream-577.php",
      "source_referer": "https://dlstreams.top/",
      "status": "ok",
      "duration_seconds": 4.93,
      "streams_count": 1,
      "streams": [
        {
          "url": "https://planetary.lovetier.bz/SkySportF1IT/index.m3u8?token=U2t5U3BvcnRGMUlUfG5vX2NoZWNrX2lwfDE3NzU5MTYyNTU=.c34ea538fa10f17478bb4001482370ba8ef26b98f3533c7dc1d3c8353667a76b",
          "referer": "https://lovetier.bz/",
          "origin": "https://lovetier.bz",
          "user_agent": "Mozilla/5.0 (Windows NT 10.0; Win64; x64) AppleWebKit/537.36 (KHTML, like Gecko) Chrome/122.0.0.0 Safari/537.36"
        }
      ]
    }
  ]
}