{
  "generated_at": "2026-04-12T16:59:42.264691+02:00",
  "total_sources": 6,
  "results": [
    {
      "source_url": "https://dlstreams.top/player/stream-877.php",
      "source_referer": "https://dlstreams.top/",
      "status": "ok",
      "duration_seconds": 8.59,
      "streams_count": 1,
      "streams": [
        {
          "url": "https://planetary.lovetier.bz/ZonaDAZN/index.m3u8?token=Wm9uYURBWk58bm9fY2hlY2tfaXB8MTc3NjAwNjIzOA==.6e77582d5bb9055f5b5b6dd07e75ee8198e065fe41071a137aaf7c52cfa7f961",
          "referer": "https://lovetier.bz/",
          "origin": "https://lovetier.bz",
          "user_agent": "Mozilla/5.0 (Windows NT 10.0; Win64; x64) AppleWebKit/537.36 (KHTML, like Gecko) Chrome/122.0.0.0 Safari/537.36"
        }
      ]
    },
    {
      "source_url": "https://dlstreams.top/player/stream-870.php",
      "source_referer": "https://dlstreams.top/",
      "status": "ok",
      "duration_seconds": 8.22,
      "streams_count": 1,
      "streams": [
        {
          "url": "https://planetary.lovetier.bz/SkySportCalcioIT/index.m3u8?token=U2t5U3BvcnRDYWxjaW9JVHxub19jaGVja19pcHwxNzc2MDA2MjQ2.c577cd1775f9a19ba1e0dbde5f2919d2419ed4c2ed43fe890ea2417121d2c80b",
          "referer": "https://lovetier.bz/",
          "origin": "https://lovetier.bz",
          "user_agent": "Mozilla/5.0 (Windows NT 10.0; Win64; x64) AppleWebKit/537.36 (KHTML, like Gecko) Chrome/122.0.0.0 Safari/537.36"
        }
      ]
    },
    {
      "source_url": "https://dlstreams.top/player/stream-461.php",
      "source_referer": "https://dlstreams.top/",
      "status": "ok",
      "duration_seconds": 9.4,
      "streams_count": 1,
      "streams": [
        {
          "url": "https://planetary.lovetier.bz/SkySportUnoIT/index.m3u8?token=U2t5U3BvcnRVbm9JVHxub19jaGVja19pcHwxNzc2MDA2MjU3.78a5a3746777c5ea2da6651cd3657c650b7c968df2f6dce170885e8f3dec9649",
          "referer": "https://lovetier.bz/",
          "origin": "https://lovetier.bz",
          "user_agent": "Mozilla/5.0 (Windows NT 10.0; Win64; x64) AppleWebKit/537.36 (KHTML, like Gecko) Chrome/122.0.0.0 Safari/537.36"
        }
      ]
    },
    {
      "source_url": "https://dlstreams.top/player/stream-576.php",
      "source_referer": "https://dlstreams.top/",
      "status": "ok",
      "duration_seconds": 8.18,
      "streams_count": 1,
      "streams": [
        {
          "url": "https://planetary.lovetier.bz/SkySportTennisIT/index.m3u8?token=U2t5U3BvcnRUZW5uaXNJVHxub19jaGVja19pcHwxNzc2MDA2MjY0.5115e705639f9d1050e90b706b12624d5dc6075bb425f104ba62035bc1083f22",
          "referer": "https://lovetier.bz/",
          "origin": "https://lovetier.bz",
          "user_agent": "Mozilla/5.0 (Windows NT 10.0; Win64; x64) AppleWebKit/537.36 (KHTML, like Gecko) Chrome/122.0.0.0 Safari/537.36"
        }
      ]
    },
    {
      "source_url": "https://dlstreams.top/player/stream-575.php",
      "source_referer": "https://dlstreams.top/",
      "status": "ok",
      "duration_seconds": 8.09,
      "streams_count": 1,
      "streams": [
        {
          "url": "https://planetary.lovetier.bz/SkySportMotoGPIT/index.m3u8?token=U2t5U3BvcnRNb3RvR1BJVHxub19jaGVja19pcHwxNzc2MDA2Mjcy.16d145a869c452bee1864cae7c9577e4314d85c230d5d0543752a3b920b83898",
          "referer": "https://lovetier.bz/",
          "origin": "https://lovetier.bz",
          "user_agent": "Mozilla/5.0 (Windows NT 10.0; Win64; x64) AppleWebKit/537.36 (KHTML, like Gecko) Chrome/122.0.0.0 Safari/537.36"
        }
      ]
    },
    {
      "source_url": "https://dlstreams.top/player/stream-577.php",
      "source_referer": "https://dlstreams.top/",
      "status": "ok",
      "duration_seconds": 7.85,
      "streams_count": 1,
      "streams": [
        {
          "url": "https://planetary.lovetier.bz/SkySportF1IT/index.m3u8?token=U2t5U3BvcnRGMUlUfG5vX2NoZWNrX2lwfDE3NzYwMDYyNzk=.55cc35f472956f5e7746702fe336bfaf23b6da09169c3d10d1fded0ed1914140",
          "referer": "https://lovetier.bz/",
          "origin": "https://lovetier.bz",
          "user_agent": "Mozilla/5.0 (Windows NT 10.0; Win64; x64) AppleWebKit/537.36 (KHTML, like Gecko) Chrome/122.0.0.0 Safari/537.36"
        }
      ]
    }
  ]
}