{
  "generated_at": "2026-03-26T18:31:55.839213+01:00",
  "total_sources": 6,
  "results": [
    {
      "source_url": "https://dlstreams.top/player/stream-877.php",
      "source_referer": "https://dlstreams.top/",
      "status": "ok",
      "duration_seconds": 4.3,
      "streams_count": 1,
      "streams": [
        {
          "url": "https://beautifulpeople.lovecdn.ru/ZonaDAZN/index.m3u8?token=Wm9uYURBWk58bm9fY2hlY2tfaXB8MTc3NDU0NjU4Ng==.fe45b8b7055f9d288d4d7887beae322f6690c8ad7efa4a0716beab65566b3532",
          "referer": "https://lovetier.bz/",
          "origin": "https://lovetier.bz",
          "user_agent": "Mozilla/5.0 (Windows NT 10.0; Win64; x64) AppleWebKit/537.36 (KHTML, like Gecko) Chrome/122.0.0.0 Safari/537.36"
        }
      ]
    },
    {
      "source_url": "https://dlstreams.top/player/stream-870.php",
      "source_referer": "https://dlstreams.top/",
      "status": "ok",
      "duration_seconds": 4.52,
      "streams_count": 1,
      "streams": [
        {
          "url": "https://beautifulpeople.lovecdn.ru/SkySportCalcioIT/index.m3u8?token=U2t5U3BvcnRDYWxjaW9JVHxub19jaGVja19pcHwxNzc0NTQ2NTkx.b50de54b97bae6d94b37aec63c0af843c0d1f8ea123fe3adbcb1d8fa33527e17",
          "referer": "https://lovetier.bz/",
          "origin": "https://lovetier.bz",
          "user_agent": "Mozilla/5.0 (Windows NT 10.0; Win64; x64) AppleWebKit/537.36 (KHTML, like Gecko) Chrome/122.0.0.0 Safari/537.36"
        }
      ]
    },
    {
      "source_url": "https://dlstreams.top/player/stream-461.php",
      "source_referer": "https://dlstreams.top/",
      "status": "ok",
      "duration_seconds": 5.37,
      "streams_count": 1,
      "streams": [
        {
          "url": "https://beautifulpeople.lovecdn.ru/SkySportUnoIT/index.m3u8?token=U2t5U3BvcnRVbm9JVHxub19jaGVja19pcHwxNzc0NTQ2NTk2.b5a2c5bb0444f1e11426f3ed0105a72765c385f26796ec2a18f8865a033a901b",
          "referer": "https://lovetier.bz/",
          "origin": "https://lovetier.bz",
          "user_agent": "Mozilla/5.0 (Windows NT 10.0; Win64; x64) AppleWebKit/537.36 (KHTML, like Gecko) Chrome/122.0.0.0 Safari/537.36"
        }
      ]
    },
    {
      "source_url": "https://dlstreams.top/player/stream-576.php",
      "source_referer": "https://dlstreams.top/",
      "status": "ok",
      "duration_seconds": 5.82,
      "streams_count": 1,
      "streams": [
        {
          "url": "https://beautifulpeople.lovecdn.ru/SkySportTennisIT/index.m3u8?token=U2t5U3BvcnRUZW5uaXNJVHxub19jaGVja19pcHwxNzc0NTQ2NjAx.23f9c50ebc5c1cc59b5f4887afc2a2211dd4bb5d2f5ac58e8146d063819d0982",
          "referer": "https://lovetier.bz/",
          "origin": "https://lovetier.bz",
          "user_agent": "Mozilla/5.0 (Windows NT 10.0; Win64; x64) AppleWebKit/537.36 (KHTML, like Gecko) Chrome/122.0.0.0 Safari/537.36"
        }
      ]
    },
    {
      "source_url": "https://dlstreams.top/player/stream-575.php",
      "source_referer": "https://dlstreams.top/",
      "status": "ok",
      "duration_seconds": 5.67,
      "streams_count": 1,
      "streams": [
        {
          "url": "https://beautifulpeople.lovecdn.ru/SkySportMotoGPIT/index.m3u8?token=U2t5U3BvcnRNb3RvR1BJVHxub19jaGVja19pcHwxNzc0NTQ2NjA3.e440c638f344719e7eb7496f63c99a0072d4999886de931ee178bcef7a5c71a8",
          "referer": "https://lovetier.bz/",
          "origin": "https://lovetier.bz",
          "user_agent": "Mozilla/5.0 (Windows NT 10.0; Win64; x64) AppleWebKit/537.36 (KHTML, like Gecko) Chrome/122.0.0.0 Safari/537.36"
        }
      ]
    },
    {
      "source_url": "https://dlstreams.top/player/stream-577.php",
      "source_referer": "https://dlstreams.top/",
      "status": "ok",
      "duration_seconds": 6.23,
      "streams_count": 1,
      "streams": [
        {
          "url": "https://beautifulpeople.lovecdn.ru/SkySportF1IT/index.m3u8?token=U2t5U3BvcnRGMUlUfG5vX2NoZWNrX2lwfDE3NzQ1NDY2MTM=.81021c3d6fb8eebda9c65049528a4098c1b74f9d1f739d97e44035876a24416d",
          "referer": "https://lovetier.bz/",
          "origin": "https://lovetier.bz",
          "user_agent": "Mozilla/5.0 (Windows NT 10.0; Win64; x64) AppleWebKit/537.36 (KHTML, like Gecko) Chrome/122.0.0.0 Safari/537.36"
        }
      ]
    }
  ]
}