{
  "generated_at": "2026-04-11T14:27:10.922044+00:00",
  "total_sources": 6,
  "results": [
    {
      "source_url": "https://dlstreams.top/player/stream-877.php",
      "source_referer": "https://dlstreams.top/",
      "status": "ok",
      "duration_seconds": 4.78,
      "streams_count": 1,
      "streams": [
        {
          "url": "https://planetary.lovetier.bz/ZonaDAZN/index.m3u8?token=Wm9uYURBWk58bm9fY2hlY2tfaXB8MTc3NTkxNzkwNA==.a1526697a03d4f89df215bd1c0f3cc1b6aebfaa226bbedc40d2366202f9a416f",
          "referer": "https://lovetier.bz/",
          "origin": "https://lovetier.bz",
          "user_agent": "Mozilla/5.0 (Windows NT 10.0; Win64; x64) AppleWebKit/537.36 (KHTML, like Gecko) Chrome/122.0.0.0 Safari/537.36"
        }
      ]
    },
    {
      "source_url": "https://dlstreams.top/player/stream-870.php",
      "source_referer": "https://dlstreams.top/",
      "status": "ok",
      "duration_seconds": 4.84,
      "streams_count": 1,
      "streams": [
        {
          "url": "https://planetary.lovetier.bz/SkySportCalcioIT/index.m3u8?token=U2t5U3BvcnRDYWxjaW9JVHxub19jaGVja19pcHwxNzc1OTE3OTEw.3a3427bf9a9ba04a34dfdb08673d240a1e96e3340f1eaf5ab730ea7f49340123",
          "referer": "https://lovetier.bz/",
          "origin": "https://lovetier.bz",
          "user_agent": "Mozilla/5.0 (Windows NT 10.0; Win64; x64) AppleWebKit/537.36 (KHTML, like Gecko) Chrome/122.0.0.0 Safari/537.36"
        }
      ]
    },
    {
      "source_url": "https://dlstreams.top/player/stream-461.php",
      "source_referer": "https://dlstreams.top/",
      "status": "ok",
      "duration_seconds": 5.77,
      "streams_count": 1,
      "streams": [
        {
          "url": "https://planetary.lovetier.bz/SkySportUnoIT/index.m3u8?token=U2t5U3BvcnRVbm9JVHxub19jaGVja19pcHwxNzc1OTE3OTE1.44c0215938dfa0094fd54d99d191496a12f4b94f10f43995087c923228e0e005",
          "referer": "https://lovetier.bz/",
          "origin": "https://lovetier.bz",
          "user_agent": "Mozilla/5.0 (Windows NT 10.0; Win64; x64) AppleWebKit/537.36 (KHTML, like Gecko) Chrome/122.0.0.0 Safari/537.36"
        }
      ]
    },
    {
      "source_url": "https://dlstreams.top/player/stream-576.php",
      "source_referer": "https://dlstreams.top/",
      "status": "ok",
      "duration_seconds": 4.92,
      "streams_count": 1,
      "streams": [
        {
          "url": "https://planetary.lovetier.bz/SkySportTennisIT/index.m3u8?token=U2t5U3BvcnRUZW5uaXNJVHxub19jaGVja19pcHwxNzc1OTE3OTIx.94fb977f8a171b24242a6b858a4d34a59b2b2daefb1015b98152c65bc499b85e",
          "referer": "https://lovetier.bz/",
          "origin": "https://lovetier.bz",
          "user_agent": "Mozilla/5.0 (Windows NT 10.0; Win64; x64) AppleWebKit/537.36 (KHTML, like Gecko) Chrome/122.0.0.0 Safari/537.36"
        }
      ]
    },
    {
      "source_url": "https://dlstreams.top/player/stream-575.php",
      "source_referer": "https://dlstreams.top/",
      "status": "ok",
      "duration_seconds": 4.56,
      "streams_count": 1,
      "streams": [
        {
          "url": "https://planetary.lovetier.bz/SkySportMotoGPIT/index.m3u8?token=U2t5U3BvcnRNb3RvR1BJVHxub19jaGVja19pcHwxNzc1OTE3OTI2.24200f0bb07b9cac9ea062efe6cd90f1ca26c8e0731c72b7ef59c68ca314107c",
          "referer": "https://lovetier.bz/",
          "origin": "https://lovetier.bz",
          "user_agent": "Mozilla/5.0 (Windows NT 10.0; Win64; x64) AppleWebKit/537.36 (KHTML, like Gecko) Chrome/122.0.0.0 Safari/537.36"
        }
      ]
    },
    {
      "source_url": "https://dlstreams.top/player/stream-577.php",
      "source_referer": "https://dlstreams.top/",
      "status": "ok",
      "duration_seconds": 4.76,
      "streams_count": 1,
      "streams": [
        {
          "url": "https://planetary.lovetier.bz/SkySportF1IT/index.m3u8?token=U2t5U3BvcnRGMUlUfG5vX2NoZWNrX2lwfDE3NzU5MTc5MzA=.ec3d4facef61d91bee3bce6bf092f2ee57db0607c1024408dac4c2fa648662c6",
          "referer": "https://lovetier.bz/",
          "origin": "https://lovetier.bz",
          "user_agent": "Mozilla/5.0 (Windows NT 10.0; Win64; x64) AppleWebKit/537.36 (KHTML, like Gecko) Chrome/122.0.0.0 Safari/537.36"
        }
      ]
    }
  ]
}