{
  "generated_at": "2026-03-21T13:34:28.301270+01:00",
  "total_sources": 6,
  "results": [
    {
      "source_url": "https://dlstreams.top/player/stream-877.php",
      "source_referer": "https://dlstreams.top/",
      "status": "ok",
      "duration_seconds": 6.7,
      "streams_count": 0,
      "streams": []
    },
    {
      "source_url": "https://dlstreams.top/player/stream-870.php",
      "source_referer": "https://dlstreams.top/",
      "status": "ok",
      "duration_seconds": 936.58,
      "streams_count": 0,
      "streams": []
    },
    {
      "source_url": "https://dlstreams.top/player/stream-461.php",
      "source_referer": "https://dlstreams.top/",
      "status": "ok",
      "duration_seconds": 1957.16,
      "streams_count": 0,
      "streams": []
    },
    {
      "source_url": "https://dlstreams.top/player/stream-576.php",
      "source_referer": "https://dlstreams.top/",
      "status": "ok",
      "duration_seconds": 19.58,
      "streams_count": 0,
      "streams": []
    },
    {
      "source_url": "https://dlstreams.top/player/stream-575.php",
      "source_referer": "https://dlstreams.top/",
      "status": "ok",
      "duration_seconds": 5.77,
      "streams_count": 0,
      "streams": []
    },
    {
      "source_url": "https://dlstreams.top/player/stream-577.php",
      "source_referer": "https://dlstreams.top/",
      "status": "ok",
      "duration_seconds": 5.67,
      "streams_count": 0,
      "streams": []
    }
  ]
}