{
  "generated_at": "2026-03-24T14:31:13.736631+01:00",
  "total_sources": 6,
  "results": [
    {
      "source_url": "https://dlstreams.top/player/stream-877.php",
      "source_referer": "https://dlstreams.top/",
      "status": "ok",
      "duration_seconds": 182.61,
      "streams_count": 0,
      "streams": []
    },
    {
      "source_url": "https://dlstreams.top/player/stream-870.php",
      "source_referer": "https://dlstreams.top/",
      "status": "ok",
      "duration_seconds": 4.83,
      "streams_count": 1,
      "streams": [
        {
          "url": "https://planetary.lovecdn.ru/SkySportCalcioIT/index.m3u8?token=U2t5U3BvcnRDYWxjaW9JVHxub19jaGVja19pcHwxNzc0MzU5MzU2.1af77170040788bf66ef9e7a26e8e6a09033d124a6303e8318dd59d0eeaa39c9",
          "referer": "https://lovetier.bz/",
          "origin": "https://lovetier.bz",
          "user_agent": "Mozilla/5.0 (Windows NT 10.0; Win64; x64) AppleWebKit/537.36 (KHTML, like Gecko) Chrome/122.0.0.0 Safari/537.36"
        }
      ]
    },
    {
      "source_url": "https://dlstreams.top/player/stream-461.php",
      "source_referer": "https://dlstreams.top/",
      "status": "ok",
      "duration_seconds": 3.71,
      "streams_count": 1,
      "streams": [
        {
          "url": "https://planetary.lovecdn.ru/SkySportUnoIT/index.m3u8?token=U2t5U3BvcnRVbm9JVHxub19jaGVja19pcHwxNzc0MzU5MzYw.25e1e60a4cabb0ba9ce1024596f7a96ed0a19bc775391d7c25a5842a28af208f",
          "referer": "https://lovetier.bz/",
          "origin": "https://lovetier.bz",
          "user_agent": "Mozilla/5.0 (Windows NT 10.0; Win64; x64) AppleWebKit/537.36 (KHTML, like Gecko) Chrome/122.0.0.0 Safari/537.36"
        }
      ]
    },
    {
      "source_url": "https://dlstreams.top/player/stream-576.php",
      "source_referer": "https://dlstreams.top/",
      "status": "ok",
      "duration_seconds": 3.67,
      "streams_count": 1,
      "streams": [
        {
          "url": "https://planetary.lovecdn.ru/SkySportTennisIT/index.m3u8?token=U2t5U3BvcnRUZW5uaXNJVHxub19jaGVja19pcHwxNzc0MzU5MzY0.b9679106ffd4987dbdac7ee7ed40bef58bdd5ccd64b7b2ee9e2ffb7830dec4a6",
          "referer": "https://lovetier.bz/",
          "origin": "https://lovetier.bz",
          "user_agent": "Mozilla/5.0 (Windows NT 10.0; Win64; x64) AppleWebKit/537.36 (KHTML, like Gecko) Chrome/122.0.0.0 Safari/537.36"
        }
      ]
    },
    {
      "source_url": "https://dlstreams.top/player/stream-575.php",
      "source_referer": "https://dlstreams.top/",
      "status": "ok",
      "duration_seconds": 3.7,
      "streams_count": 1,
      "streams": [
        {
          "url": "https://planetary.lovecdn.ru/SkySportMotoGPIT/index.m3u8?token=U2t5U3BvcnRNb3RvR1BJVHxub19jaGVja19pcHwxNzc0MzU5MzY3.3c3841617df66af154f84e5db256a2c3d78425cd89ae475cde601b0ca6c12366",
          "referer": "https://lovetier.bz/",
          "origin": "https://lovetier.bz",
          "user_agent": "Mozilla/5.0 (Windows NT 10.0; Win64; x64) AppleWebKit/537.36 (KHTML, like Gecko) Chrome/122.0.0.0 Safari/537.36"
        }
      ]
    },
    {
      "source_url": "https://dlstreams.top/player/stream-577.php",
      "source_referer": "https://dlstreams.top/",
      "status": "ok",
      "duration_seconds": 4.92,
      "streams_count": 1,
      "streams": [
        {
          "url": "https://planetary.lovecdn.ru/SkySportF1IT/index.m3u8?token=U2t5U3BvcnRGMUlUfG5vX2NoZWNrX2lwfDE3NzQzNTkzNzI=.fd6784d892fcf8313f06940cc1d6e8c0ab1a65b6d5fd0c587e4c86e9116f078e",
          "referer": "https://lovetier.bz/",
          "origin": "https://lovetier.bz",
          "user_agent": "Mozilla/5.0 (Windows NT 10.0; Win64; x64) AppleWebKit/537.36 (KHTML, like Gecko) Chrome/122.0.0.0 Safari/537.36"
        }
      ]
    }
  ]
}