{
  "generated_at": "2026-04-11T14:43:52.453692+00:00",
  "total_sources": 6,
  "results": [
    {
      "source_url": "https://dlstreams.top/player/stream-877.php",
      "source_referer": "https://dlstreams.top/",
      "status": "ok",
      "duration_seconds": 5.01,
      "streams_count": 1,
      "streams": [
        {
          "url": "https://planetary.lovetier.bz/ZonaDAZN/index.m3u8?token=Wm9uYURBWk58bm9fY2hlY2tfaXB8MTc3NTkxODkwNg==.4e11595d830bb119567783ce4975409fd6d7500d2f6a02747a20e8dc958a1666",
          "referer": "https://lovetier.bz/",
          "origin": "https://lovetier.bz",
          "user_agent": "Mozilla/5.0 (Windows NT 10.0; Win64; x64) AppleWebKit/537.36 (KHTML, like Gecko) Chrome/122.0.0.0 Safari/537.36"
        }
      ]
    },
    {
      "source_url": "https://dlstreams.top/player/stream-870.php",
      "source_referer": "https://dlstreams.top/",
      "status": "ok",
      "duration_seconds": 5.51,
      "streams_count": 1,
      "streams": [
        {
          "url": "https://planetary.lovetier.bz/SkySportCalcioIT/index.m3u8?token=U2t5U3BvcnRDYWxjaW9JVHxub19jaGVja19pcHwxNzc1OTE4OTEx.e63e888361a679fd38e1345679c5f79aa6e9088e9a31413012f99fafba138a6f",
          "referer": "https://lovetier.bz/",
          "origin": "https://lovetier.bz",
          "user_agent": "Mozilla/5.0 (Windows NT 10.0; Win64; x64) AppleWebKit/537.36 (KHTML, like Gecko) Chrome/122.0.0.0 Safari/537.36"
        }
      ]
    },
    {
      "source_url": "https://dlstreams.top/player/stream-461.php",
      "source_referer": "https://dlstreams.top/",
      "status": "ok",
      "duration_seconds": 4.46,
      "streams_count": 1,
      "streams": [
        {
          "url": "https://planetary.lovetier.bz/SkySportUnoIT/index.m3u8?token=U2t5U3BvcnRVbm9JVHxub19jaGVja19pcHwxNzc1OTE4OTE2.947579071cf72f3873568ac0b072c930701ec8d71c14ef2af82e24c46e65ffc8",
          "referer": "https://lovetier.bz/",
          "origin": "https://lovetier.bz",
          "user_agent": "Mozilla/5.0 (Windows NT 10.0; Win64; x64) AppleWebKit/537.36 (KHTML, like Gecko) Chrome/122.0.0.0 Safari/537.36"
        }
      ]
    },
    {
      "source_url": "https://dlstreams.top/player/stream-576.php",
      "source_referer": "https://dlstreams.top/",
      "status": "ok",
      "duration_seconds": 5.51,
      "streams_count": 1,
      "streams": [
        {
          "url": "https://planetary.lovetier.bz/SkySportTennisIT/index.m3u8?token=U2t5U3BvcnRUZW5uaXNJVHxub19jaGVja19pcHwxNzc1OTE4OTIz.619ada392e83ed9f4f5ec00a3c39068d99b1703362ec78f91caa9f3c5e8cde09",
          "referer": "https://lovetier.bz/",
          "origin": "https://lovetier.bz",
          "user_agent": "Mozilla/5.0 (Windows NT 10.0; Win64; x64) AppleWebKit/537.36 (KHTML, like Gecko) Chrome/122.0.0.0 Safari/537.36"
        }
      ]
    },
    {
      "source_url": "https://dlstreams.top/player/stream-575.php",
      "source_referer": "https://dlstreams.top/",
      "status": "ok",
      "duration_seconds": 5.13,
      "streams_count": 1,
      "streams": [
        {
          "url": "https://planetary.lovetier.bz/SkySportMotoGPIT/index.m3u8?token=U2t5U3BvcnRNb3RvR1BJVHxub19jaGVja19pcHwxNzc1OTE4OTI4.5638945b54862dda6d0fd2878689e3850d2969c962b570af6e4cf6c463a817c5",
          "referer": "https://lovetier.bz/",
          "origin": "https://lovetier.bz",
          "user_agent": "Mozilla/5.0 (Windows NT 10.0; Win64; x64) AppleWebKit/537.36 (KHTML, like Gecko) Chrome/122.0.0.0 Safari/537.36"
        }
      ]
    },
    {
      "source_url": "https://dlstreams.top/player/stream-577.php",
      "source_referer": "https://dlstreams.top/",
      "status": "ok",
      "duration_seconds": 4.6,
      "streams_count": 1,
      "streams": [
        {
          "url": "https://planetary.lovetier.bz/SkySportF1IT/index.m3u8?token=U2t5U3BvcnRGMUlUfG5vX2NoZWNrX2lwfDE3NzU5MTg5MzI=.c6345d3096c2b3d2930fa0ffe14b6de51a68eadd002958cc41d619b394f08f20",
          "referer": "https://lovetier.bz/",
          "origin": "https://lovetier.bz",
          "user_agent": "Mozilla/5.0 (Windows NT 10.0; Win64; x64) AppleWebKit/537.36 (KHTML, like Gecko) Chrome/122.0.0.0 Safari/537.36"
        }
      ]
    }
  ]
}